filez_python_sdk/__init__.py
filez_python_sdk/cli.py
filez_python_sdk/filez_python_sdk.py
filez_python_sdk-0.0.1.dist-info/entry_points.txt
filez_python_sdk-0.0.1.dist-info/LICENSE
filez_python_sdk-0.0.1.dist-info/WHEEL
filez_python_sdk-0.0.1.dist-info/METADATA
filez_python_sdk-0.0.1.dist-info/RECORD
